firex_blaze/__init__.py
firex_blaze/__main__.py
firex_blaze/_version.py
firex_blaze/blaze_event_consumer.py
firex_blaze/blaze_helper.py
firex_blaze/blaze_launcher.py
firex_blaze/fast_blaze_helper.py
firex_blaze-1.26.dist-info/LICENSE
firex_blaze-1.26.dist-info/METADATA
firex_blaze-1.26.dist-info/WHEEL
firex_blaze-1.26.dist-info/entry_points.txt
firex_blaze-1.26.dist-info/top_level.txt
firex_blaze-1.26.dist-info/zip-safe
firex_blaze-1.26.dist-info/RECORD
