Metadata-Version: 2.1
Name: firex-blaze
Version: 1.26
Summary: FireX event processor for submitting to a kafka bus.
Home-page: https://github.com/FireXStuff/firex-blaze
Author: Core FireX Team
Author-email: firex-dev@gmail.com
License: BSD-3-Clause
Platform: UNKNOWN
License-File: LICENSE
Requires-Dist: firexapp
Requires-Dist: confluent-kafka==2.12.0
